asktanya/__init__.py
asktanya/clean.py
asktanya/func.py
asktanya/main.py
asktanya/data/.keep
asktanya-1.0.17.data/scripts/ask-tanya
tests/__init__.py
asktanya-1.0.17.dist-info/METADATA
asktanya-1.0.17.dist-info/WHEEL
asktanya-1.0.17.dist-info/top_level.txt
asktanya-1.0.17.dist-info/RECORD
