Metadata-Version: 2.1
Name: asktanya
Version: 1.0.17
Summary: Ask-tanya anything! Asktanya is a Python framework to search factual information on the internet.
Requires-Dist: wikipedia
Requires-Dist: pywikihow
Requires-Dist: beautifulsoup4
Requires-Dist: requests
Requires-Dist: nltk
Requires-Dist: black
Requires-Dist: flake8
